genepy/__init__.py
genepy/core.py
genepy/node.py
genepy/tree.py
genepy-1.0.0b1.dist-info/DESCRIPTION.rst
genepy-1.0.0b1.dist-info/METADATA
genepy-1.0.0b1.dist-info/RECORD
genepy-1.0.0b1.dist-info/WHEEL
genepy-1.0.0b1.dist-info/metadata.json
genepy-1.0.0b1.dist-info/top_level.txt
genetic/__init__.py
genetic/core.py
genetic/node.py
genetic/tree.py
