Metadata-Version: 2.0
Name: genepy
Version: 1.0.0b1
Summary: Simple genetic programming library using tree representation for individuals
Home-page: https://github.com/amstuta/genetic.py
Author: Arthur Amstutz
Author-email: arthur.amstutz@gmail.com
License: MIT
Keywords: genetic evolution intelligence data learning
Platform: UNKNOWN
Classifier: Development Status :: 4 - Beta
Classifier: Intended Audience :: Developers
Classifier: Topic :: Scientific/Engineering :: Artificial Intelligence
Classifier: License :: OSI Approved :: MIT License
Classifier: Programming Language :: Python :: 2.7
Classifier: Programming Language :: Python :: 3
Classifier: Programming Language :: Python :: 3.0
Classifier: Programming Language :: Python :: 3.1
Classifier: Programming Language :: Python :: 3.2
Classifier: Programming Language :: Python :: 3.3
Classifier: Programming Language :: Python :: 3.4
Classifier: Programming Language :: Python :: 3.5
Classifier: Programming Language :: Python :: 3.6
